LICENSE
MANIFEST.in
README.md
setup.py
test_haha/__init__.py
test_haha/__version__.py
test_haha/core.py
test_haha.egg-info/PKG-INFO
test_haha.egg-info/SOURCES.txt
test_haha.egg-info/dependency_links.txt
test_haha.egg-info/top_level.txt